bitsrun/__init__.py
bitsrun/cli.py
bitsrun/config.py
bitsrun/models.py
bitsrun/user.py
bitsrun/utils.py
bitsrun-3.7.1.dist-info/LICENSE
bitsrun-3.7.1.dist-info/METADATA
bitsrun-3.7.1.dist-info/WHEEL
bitsrun-3.7.1.dist-info/entry_points.txt
bitsrun-3.7.1.dist-info/top_level.txt
bitsrun-3.7.1.dist-info/RECORD
