Metadata-Version: 2.1
Name: bitsrun
Version: 3.7.1
Summary: A headless login / logout script for 10.0.0.55
Author-email: spencerwooo <spencer.woo@outlook.com>
License: WTFPL
Project-URL: homepage, https://github.com/BITNP/bitsrun
Keywords: bit,srun,srun-login,srun-client,beijing-institute-of-technology
Classifier: Development Status :: 5 - Production/Stable
Classifier: Environment :: Console
Classifier: Intended Audience :: Developers
Classifier: Intended Audience :: Education
Classifier: Intended Audience :: End Users/Desktop
Classifier: Intended Audience :: Information Technology
Classifier: Operating System :: OS Independent
Classifier: Programming Language :: Python :: 3
Classifier: Programming Language :: Python :: 3.8
Classifier: Programming Language :: Python :: 3.9
Classifier: Programming Language :: Python :: 3.10
Classifier: Programming Language :: Python :: 3.11
Classifier: Programming Language :: Python :: 3.12
Classifier: Topic :: Education
Classifier: Topic :: Internet
Requires-Python: >=3.8
License-File: LICENSE
Requires-Dist: httpx >=0.24.0
Requires-Dist: rich >=13.3.5
Requires-Dist: humanize >=4.5.0
Requires-Dist: click >=8.1.3
Requires-Dist: platformdirs >=2.6.2
